dycw_nitpick/__init__.py
dycw_nitpick-0.0.34.dist-info/METADATA
dycw_nitpick-0.0.34.dist-info/WHEEL
dycw_nitpick-0.0.34.dist-info/RECORD
