Metadata-Version: 2.1
Name: dycw-nitpick
Version: 0.0.34
Author-email: Derek Wan <d.wan@icloud.com>
Requires-Python: >=3.9
Provides-Extra: dev
Requires-Dist: black; extra == 'dev'
Requires-Dist: exceptiongroup; extra == 'dev'
Requires-Dist: hatch; extra == 'dev'
Requires-Dist: pip-tools; extra == 'dev'
Requires-Dist: pytest; extra == 'dev'
Requires-Dist: pytest-cov; extra == 'dev'
Requires-Dist: pytest-xdist; extra == 'dev'
Requires-Dist: ruff; extra == 'dev'
